[
  {
    "idx": 1,
    "file": "IMG_5343.JPG",
    "size": [
      5616,
      3744
    ],
    "sharp": 569.38,
    "brightness": 19.2
  },
  {
    "idx": 2,
    "file": "IMG_5345.JPG",
    "size": [
      5616,
      3744
    ],
    "sharp": 1003.14,
    "brightness": 24.5
  },
  {
    "idx": 3,
    "file": "IMG_5346.JPG",
    "size": [
      5616,
      3744
    ],
    "sharp": 1000.44,
    "brightness": 22.4
  },
  {
    "idx": 4,
    "file": "IMG_5350.JPG",
    "size": [
      5616,
      3744
    ],
    "sharp": 761.16,
    "brightness": 21.1
  },
  {
    "idx": 5,
    "file": "IMG_5348.JPG",
    "size": [
      5616,
      3744
    ],
    "sharp": 784.33,
    "brightness": 22.7
  },
  {
    "idx": 6,
    "file": "IMG_5307.JPG",
    "size": [
      5616,
      3744
    ],
    "sharp": 927.14,
    "brightness": 20.9
  },
  {
    "idx": 7,
    "file": "IMG_5349.JPG",
    "size": [
      5616,
      3744
    ],
    "sharp": 1078.22,
    "brightness": 22.2
  },
  {
    "idx": 8,
    "file": "IMG_5355.JPG",
    "size": [
      5616,
      3744
    ],
    "sharp": 1418.25,
    "brightness": 28.2
  },
  {
    "idx": 9,
    "file": "IMG_5308.JPG",
    "size": [
      5616,
      3744
    ],
    "sharp": 1006.74,
    "brightness": 20.8
  },
  {
    "idx": 10,
    "file": "IMG_5315.JPG",
    "size": [
      5616,
      3744
    ],
    "sharp": 919.94,
    "brightness": 30.2
  },
  {
    "idx": 11,
    "file": "IMG_5322.JPG",
    "size": [
      5616,
      3744
    ],
    "sharp": 778.2,
    "brightness": 22.2
  },
  {
    "idx": 12,
    "file": "IMG_5317.JPG",
    "size": [
      5616,
      3744
    ],
    "sharp": 1017.07,
    "brightness": 33.8
  },
  {
    "idx": 13,
    "file": "IMG_5311.JPG",
    "size": [
      5616,
      3744
    ],
    "sharp": 1123.94,
    "brightness": 28.7
  },
  {
    "idx": 14,
    "file": "IMG_5319.JPG",
    "size": [
      5616,
      3744
    ],
    "sharp": 993.37,
    "brightness": 31.4
  },
  {
    "idx": 15,
    "file": "IMG_5310.JPG",
    "size": [
      5616,
      3744
    ],
    "sharp": 1505.74,
    "brightness": 33.0
  },
  {
    "idx": 16,
    "file": "IMG_5325.JPG",
    "size": [
      5616,
      3744
    ],
    "sharp": 1046.2,
    "brightness": 29.4
  },
  {
    "idx": 17,
    "file": "IMG_5328.JPG",
    "size": [
      5616,
      3744
    ],
    "sharp": 985.51,
    "brightness": 26.3
  },
  {
    "idx": 18,
    "file": "IMG_5323.JPG",
    "size": [
      5616,
      3744
    ],
    "sharp": 1746.96,
    "brightness": 54.0
  },
  {
    "idx": 19,
    "file": "IMG_5330.JPG",
    "size": [
      5616,
      3744
    ],
    "sharp": 1013.42,
    "brightness": 28.7
  },
  {
    "idx": 20,
    "file": "IMG_5324.JPG",
    "size": [
      5616,
      3744
    ],
    "sharp": 1645.41,
    "brightness": 53.8
  },
  {
    "idx": 21,
    "file": "IMG_5334.JPG",
    "size": [
      5616,
      3744
    ],
    "sharp": 1298.3,
    "brightness": 32.2
  },
  {
    "idx": 22,
    "file": "IMG_5336.JPG",
    "size": [
      5616,
      3744
    ],
    "sharp": 896.96,
    "brightness": 32.0
  },
  {
    "idx": 23,
    "file": "IMG_5338.JPG",
    "size": [
      5616,
      3744
    ],
    "sharp": 1319.65,
    "brightness": 26.3
  },
  {
    "idx": 24,
    "file": "IMG_5337.JPG",
    "size": [
      5616,
      3744
    ],
    "sharp": 1386.19,
    "brightness": 26.7
  },
  {
    "idx": 25,
    "file": "IMG_5341.JPG",
    "size": [
      5616,
      3744
    ],
    "sharp": 1572.46,
    "brightness": 28.0
  }
]